surveyhelper/__init__.py
surveyhelper/codebook.py
surveyhelper/frequency_report.py
surveyhelper/qsf_parser.py
surveyhelper/question.py
surveyhelper/response_set.py
surveyhelper/scale.py
surveyhelper-0.1.1.dev1.dist-info/DESCRIPTION.rst
surveyhelper-0.1.1.dev1.dist-info/METADATA
surveyhelper-0.1.1.dev1.dist-info/RECORD
surveyhelper-0.1.1.dev1.dist-info/WHEEL
surveyhelper-0.1.1.dev1.dist-info/metadata.json
surveyhelper-0.1.1.dev1.dist-info/top_level.txt
