Metadata-Version: 2.0
Name: surveyhelper
Version: 0.1.1.dev1
Summary: Survey package for reporting on survey data from Qualtrics.
Home-page: http://github.com/cwade/surveyhelper
Author: cwade
Author-email: pysurveyhelper@gmail.com
License: MIT
Platform: UNKNOWN
Requires-Dist: beautifulsoup4
Requires-Dist: jinja2
Requires-Dist: pandas
Requires-Dist: pyyaml
Requires-Dist: scipy
Requires-Dist: unidecode
